filterweb/__init__.py
filterweb/_cli.py
filterweb/_version.py
filterweb/base.py
filterweb/index.py
filterweb/filter/__init__.py
filterweb/filter/filter.py
filterweb/filter/jinja.py
filterweb/input/__init__.py
filterweb/input/file.py
filterweb/input/grpc.py
filterweb/input/http.py
filterweb/input/input.py
filterweb/input/jsonrpc.py
filterweb/input/process.py
filterweb/input/sftp.py
filterweb/input/sqlite.py
filterweb/input/ssh.py
filterweb/input/xmlrpc.py
filterweb/serve/__init__.py
filterweb/serve/http.py
filterweb/serve/serve.py
filterweb-0.0.1.dist-info/LICENSE
filterweb-0.0.1.dist-info/METADATA
filterweb-0.0.1.dist-info/WHEEL
filterweb-0.0.1.dist-info/entry_points.txt
filterweb-0.0.1.dist-info/top_level.txt
filterweb-0.0.1.dist-info/RECORD
